MANIFEST.in
README.rst
setup.cfg
setup.py
libgit2/.HEADER
libgit2/.editorconfig
libgit2/.git
libgit2/.gitattributes
libgit2/.gitignore
libgit2/.mailmap
libgit2/AUTHORS
libgit2/CMakeLists.txt
libgit2/COPYING
libgit2/README.md
libgit2/SECURITY.md
libgit2/api.docurium
libgit2/azure-pipelines.yml
libgit2/git.git-authors
libgit2/package.json
libgit2/.github/ISSUE_TEMPLATE
libgit2/.github/workflows/main.yml
libgit2/azure-pipelines/bash.yml
libgit2/azure-pipelines/build.sh
libgit2/azure-pipelines/coverity.sh
libgit2/azure-pipelines/coverity.yml
libgit2/azure-pipelines/docker.yml
libgit2/azure-pipelines/getcontainer.sh
libgit2/azure-pipelines/nightly.yml
libgit2/azure-pipelines/setup-mingw.sh
libgit2/azure-pipelines/setup-osx.sh
libgit2/azure-pipelines/test.sh
libgit2/azure-pipelines/docker/bionic
libgit2/azure-pipelines/docker/docurium
libgit2/azure-pipelines/docker/entrypoint.sh
libgit2/azure-pipelines/docker/focal
libgit2/azure-pipelines/docker/xenial
libgit2/cmake/AddCFlagIfSupported.cmake
libgit2/cmake/EnableWarnings.cmake
libgit2/cmake/FindCoreFoundation.cmake
libgit2/cmake/FindGSSAPI.cmake
libgit2/cmake/FindGSSFramework.cmake
libgit2/cmake/FindHTTP_Parser.cmake
libgit2/cmake/FindIconv.cmake
libgit2/cmake/FindPCRE.cmake
libgit2/cmake/FindPCRE2.cmake
libgit2/cmake/FindPkgLibraries.cmake
libgit2/cmake/FindSecurity.cmake
libgit2/cmake/FindStatNsec.cmake
libgit2/cmake/FindmbedTLS.cmake
libgit2/cmake/IdeSplitSources.cmake
libgit2/cmake/PkgBuildConfig.cmake
libgit2/cmake/SanitizeBool.cmake
libgit2/cmake/SelectGSSAPI.cmake
libgit2/cmake/SelectHTTPSBackend.cmake
libgit2/cmake/SelectHashes.cmake
libgit2/deps/http-parser/CMakeLists.txt
libgit2/deps/http-parser/COPYING
libgit2/deps/http-parser/http_parser.c
libgit2/deps/http-parser/http_parser.h
libgit2/deps/ntlmclient/CMakeLists.txt
libgit2/deps/ntlmclient/compat.h
libgit2/deps/ntlmclient/crypt.h
libgit2/deps/ntlmclient/crypt_commoncrypto.c
libgit2/deps/ntlmclient/crypt_commoncrypto.h
libgit2/deps/ntlmclient/crypt_mbedtls.c
venvgit2.egg-info/PKG-INFO
venvgit2.egg-info/SOURCES.txt
venvgit2.egg-info/dependency_links.txt
venvgit2.egg-info/requires.txt
venvgit2.egg-info/top_level.txt