Metadata-Version: 1.0
Name: venvgit2
Version: 1.5.0
Summary: Install libgit2 and pygit2 in a virtualenv
Home-page: https://github.com/uniphil/venvgit2
Author: uniphil
Author-email: uniphil@gmail.com
License: Public Domain
Platform: UNKNOWN
